telestream_cloud_tts/__init__.py
telestream_cloud_tts/api_client.py
telestream_cloud_tts/configuration.py
telestream_cloud_tts/rest.py
telestream_cloud_tts/api/__init__.py
telestream_cloud_tts/api/tts_api.py
telestream_cloud_tts/models/__init__.py
telestream_cloud_tts/models/corpora_collection.py
telestream_cloud_tts/models/corpus.py
telestream_cloud_tts/models/error_response.py
telestream_cloud_tts/models/extra_file.py
telestream_cloud_tts/models/fragment.py
telestream_cloud_tts/models/fragment_variant.py
telestream_cloud_tts/models/job.py
telestream_cloud_tts/models/job_result.py
telestream_cloud_tts/models/jobs_collection.py
telestream_cloud_tts/models/project.py
telestream_cloud_tts/models/projects_collection.py
telestream_cloud_tts/models/result.py
telestream_cloud_tts/models/upload_file.py
telestream_cloud_tts/models/upload_session.py
telestream_cloud_tts/models/uploader.py
telestream_cloud_tts/models/video_upload_body.py
telestream_cloud_tts-2.0.0.dist-info/DESCRIPTION.rst
telestream_cloud_tts-2.0.0.dist-info/METADATA
telestream_cloud_tts-2.0.0.dist-info/RECORD
telestream_cloud_tts-2.0.0.dist-info/WHEEL
telestream_cloud_tts-2.0.0.dist-info/metadata.json
telestream_cloud_tts-2.0.0.dist-info/top_level.txt
test/__init__.py
test/test_corpora_collection.py
test/test_corpus.py
test/test_error_response.py
test/test_extra_file.py
test/test_fragment.py
test/test_fragment_variant.py
test/test_job.py
test/test_job_result.py
test/test_jobs_collection.py
test/test_project.py
test/test_projects_collection.py
test/test_result.py
test/test_tts_api.py
test/test_upload_session.py
test/test_video_upload_body.py
