Metadata-Version: 2.0
Name: telestream-cloud-tts
Version: 2.0.0
Summary: Tts API
Home-page: https://github.com/telestream/telestream-cloud-python-sdk
Author: UNKNOWN
Author-email: cloudsupport@telestream.net
License: UNKNOWN
Keywords: Swagger,Tts API
Platform: UNKNOWN
Requires-Dist: urllib3 (>=1.15)
Requires-Dist: six (>=1.10)
Requires-Dist: certifi
Requires-Dist: python-dateutil
Requires-Dist: requests
